hydromt_dash_app/__init__.py
hydromt_dash_app/api.py
hydromt_dash_app/app.py
hydromt_dash_app/callbacks.py
hydromt_dash_app/functions.py
hydromt_dash_app/layouts.py
hydromt_dash_app/run_app.py
hydromt_dash_app/styling.py
hydromt_dash_app/assets/01_tab_style.css
hydromt_dash_app/assets/favicon.ico
hydromt_dash_app-0.0.1.dist-info/entry_points.txt
hydromt_dash_app-0.0.1.dist-info/LICENSE
hydromt_dash_app-0.0.1.dist-info/WHEEL
hydromt_dash_app-0.0.1.dist-info/METADATA
hydromt_dash_app-0.0.1.dist-info/RECORD
