Metadata-Version: 2.1
Name: hydromt-dash-app
Version: 0.0.1
Summary: HydroMT dashboard: A dashboard interface to the HydroMT environment
Author-email: Tjalling de Jong <tjalling.dejong@deltares.nl>, Dirk Eilander <dirk.eilander@deltares.nl>
Requires-Python: >=3.8
Classifier: Intended Audience :: Developers
Classifier: Intended Audience :: Science/Research
Classifier: Topic :: Scientific/Engineering :: Hydrology
Classifier: License :: OSI Approved :: MIT License
Classifier: Programming Language :: Python :: 3
Requires-Dist: hydromt
Requires-Dist: dash>=2.6.2
Requires-Dist: dash-bootstrap-components>=1.2.0
Requires-Dist: visdcc
Requires-Dist: dash-extensions>=0.0.71
Requires-Dist: dash-leaflet>=0.1.23
Requires-Dist: geojson
Project-URL: Home, https://github.com/Deltares/hydromt_dash
